pynxtools_xps/__init__.py
pynxtools_xps/mkdocs.py
pynxtools_xps/reader.py
pynxtools_xps/reader_utils.py
pynxtools_xps/value_mappers.py
pynxtools_xps/config/config_phi.json
pynxtools_xps/config/config_scienta.json
pynxtools_xps/config/config_scienta_hdf5.json
pynxtools_xps/config/config_specs_sle.json
pynxtools_xps/config/config_specs_xml.json
pynxtools_xps/config/config_specs_xy.json
pynxtools_xps/config/config_vms.json
pynxtools_xps/config/template.json
pynxtools_xps/kratos/__init__.py
pynxtools_xps/kratos/kratos_data_model.py
pynxtools_xps/kratos/metadata_kratos.py
pynxtools_xps/models/__init__.py
pynxtools_xps/models/backgrounds.py
pynxtools_xps/models/lineshapes.py
pynxtools_xps/nomad/entrypoints.py
pynxtools_xps/nomad/examples/E1 XPS data conversion to NeXus.ipynb
pynxtools_xps/nomad/examples/E2 XPS data analysis and fitting.ipynb
pynxtools_xps/nomad/examples/EX439_S718_Au_in_25_mbar_O2.sle
pynxtools_xps/nomad/examples/README.md
pynxtools_xps/nomad/examples/eln_conversion.archive.json
pynxtools_xps/nomad/examples/nexus_conversion.archive.json
pynxtools_xps/nomad/examples/xps.scheme.archive.yaml
pynxtools_xps/nomad/examples/xps_region.py
pynxtools_xps/phi/__init__.py
pynxtools_xps/phi/phi_data_model.py
pynxtools_xps/phi/spe_pro_phi.py
pynxtools_xps/scienta/__init__.py
pynxtools_xps/scienta/scienta_data_model.py
pynxtools_xps/scienta/scienta_mappings.py
pynxtools_xps/scienta/scienta_reader.py
pynxtools_xps/specs/__init__.py
pynxtools_xps/specs/sle/__init__.py
pynxtools_xps/specs/sle/sle_specs.py
pynxtools_xps/specs/slh/__init__.py
pynxtools_xps/specs/xml/__init__.py
pynxtools_xps/specs/xml/xml_specs.py
pynxtools_xps/specs/xy/__init__.py
pynxtools_xps/specs/xy/xy_specs.py
pynxtools_xps/vms/__init__.py
pynxtools_xps/vms/casa_data_model.py
pynxtools_xps/vms/vamas.py
pynxtools_xps/vms/vamas_comment_handler.py
pynxtools_xps/vms/vamas_data_model.py
pynxtools_xps/vms/vamas_export.py
pynxtools_xps-0.5.4.dist-info/licenses/LICENSE
pynxtools_xps-0.5.4.dist-info/METADATA
pynxtools_xps-0.5.4.dist-info/WHEEL
pynxtools_xps-0.5.4.dist-info/entry_points.txt
pynxtools_xps-0.5.4.dist-info/top_level.txt
pynxtools_xps-0.5.4.dist-info/RECORD
